pygaming/__init__.py
pygaming/_base.py
pygaming/color.py
pygaming/config.py
pygaming/cursor.py
pygaming/error.py
pygaming/file.py
pygaming/game.py
pygaming/logger.py
pygaming/music.py
pygaming/phase.py
pygaming/server.py
pygaming/settings.py
pygaming/state.py
pygaming/commands/__init__.py
pygaming/commands/build.py
pygaming/commands/cli.py
pygaming/commands/game_launcher.py
pygaming/commands/init_cwd.py
pygaming/commands/install.py
pygaming/commands/server_launcher.py
pygaming/commands/init_texts/asset_success.txt
pygaming/commands/init_texts/data_success.txt
pygaming/commands/init_texts/init_success.txt
pygaming/commands/init_texts/src_success.txt
pygaming/commands/templates/assets/icon.ico
pygaming/commands/templates/data/config.json
pygaming/commands/templates/data/settings.json
pygaming/commands/templates/data/state.json
pygaming/commands/templates/data/sql-game/fonts.sql
pygaming/commands/templates/data/sql-game/ig_queries.sql
pygaming/commands/templates/data/sql-game/localizations.sql
pygaming/commands/templates/data/sql-game/sounds.sql
pygaming/commands/templates/data/sql-game/speeches.sql
pygaming/commands/templates/data/sql-game/tables.sql
pygaming/commands/templates/data/sql-game/tags.sql
pygaming/commands/templates/data/sql-server/ig_queries.sql
pygaming/commands/templates/data/sql-server/tables.sql
pygaming/commands/templates/src/game.py
pygaming/commands/templates/src/server.py
pygaming/connexion/__init__.py
pygaming/connexion/_constants.py
pygaming/connexion/client.py
pygaming/connexion/server.py
pygaming/database/__init__.py
pygaming/database/database.py
pygaming/database/fonts.py
pygaming/database/sounds.py
pygaming/database/speeches.py
pygaming/database/texts.py
pygaming/inputs/__init__.py
pygaming/inputs/controls.py
pygaming/inputs/inputs.py
pygaming/inputs/keyboard.py
pygaming/inputs/mouse.py
pygaming/screen/__init__.py
pygaming/screen/_visual.py
pygaming/screen/actor.py
pygaming/screen/anchors.py
pygaming/screen/camera.py
pygaming-0.9.0.dist-info/LICENSE
pygaming-0.9.0.dist-info/METADATA
pygaming-0.9.0.dist-info/WHEEL
pygaming-0.9.0.dist-info/entry_points.txt
pygaming-0.9.0.dist-info/top_level.txt
pygaming-0.9.0.dist-info/RECORD
