Metadata-Version: 2.2
Name: pygaming
Version: 0.9.0
Summary: Pygaming is a python library based on pygame used to create game more easily by providing several tools.
Home-page: https://github.com/Tanguy-ddv/pygaming/
Author: Tanguy Dugas du Villard
Classifier: Programming Language :: Python :: 3
Classifier: Operating System :: OS Independent
Classifier: Development Status :: 3 - Alpha
Classifier: Intended Audience :: Developers
Classifier: Topic :: Games/Entertainment
Classifier: Topic :: Software Development :: Libraries :: pygame
Requires-Python: >=3.6
License-File: LICENSE
Requires-Dist: pyinstaller
Requires-Dist: pygame
Requires-Dist: numpy
Requires-Dist: gamarts
Requires-Dist: ZOCallable
Requires-Dist: pygame-cv
Dynamic: author
Dynamic: classifier
Dynamic: description
Dynamic: description-content-type
Dynamic: home-page
Dynamic: requires-dist
Dynamic: requires-python
Dynamic: summary
